<annotation><folder>VOC2007</folder><filename>25_5765613584_20180629195441_20180629215443_163.jpg</filename><size><width>787</width><height>480</height><depth>3</depth></size><segmented>0</segmented><object><name /><pose>Unspecified</pose><truncated>0</truncated><difficult>0</difficult><bndbox><xmin>115</xmin><ymin>107</ymin><xmax>449</xmax><ymax>162</ymax></bndbox></object><object><name /><pose>Unspecified</pose><truncated>0</truncated><difficult>0</difficult><bndbox><xmin>1</xmin><ymin>217</ymin><xmax>403</xmax><ymax>278</ymax></bndbox></object><object><name /><pose>Unspecified</pose><truncated>0</truncated><difficult>0</difficult><bndbox><xmin>448</xmin><ymin>46</ymin><xmax>588</xmax><ymax>114</ymax></bndbox></object><object><name /><pose>Unspecified</pose><truncated>0</truncated><difficult>0</difficult><bndbox><xmin>108</xmin><ymin>162</ymin><xmax>200</xmax><ymax>216</ymax></bndbox></object><object><name /><pose>Unspecified</pose><truncated>0</truncated><difficult>0</difficult><bndbox><xmin>214</xmin><ymin>163</ymin><xmax>319</xmax><ymax>219</ymax></bndbox></object><object><name /><pose>Unspecified</pose><truncated>0</truncated><difficult>0</difficult><bndbox><xmin>308</xmin><ymin>161</ymin><xmax>410</xmax><ymax>217</ymax></bndbox></object><object><name /><pose>Unspecified</pose><truncated>0</truncated><difficult>0</difficult><bndbox><xmin>430</xmin><ymin>159</ymin><xmax>588</xmax><ymax>225</ymax></bndbox></object></annotation>