<annotation><folder>VOC2007</folder><filename>25_5628377968_20180627163647_20180627183654_161.jpg</filename><size><width>784</width><height>388</height><depth>3</depth></size><segmented>0</segmented><object><name /><pose>Unspecified</pose><truncated>0</truncated><difficult>0</difficult><bndbox><xmin>343</xmin><ymin>99</ymin><xmax>558</xmax><ymax>136</ymax></bndbox></object><object><name /><pose>Unspecified</pose><truncated>0</truncated><difficult>0</difficult><bndbox><xmin>40</xmin><ymin>185</ymin><xmax>265</xmax><ymax>225</ymax></bndbox></object><object><name /><pose>Unspecified</pose><truncated>0</truncated><difficult>0</difficult><bndbox><xmin>48</xmin><ymin>84</ymin><xmax>171</xmax><ymax>131</ymax></bndbox></object><object><name /><pose>Unspecified</pose><truncated>0</truncated><difficult>0</difficult><bndbox><xmin>40</xmin><ymin>145</ymin><xmax>673</xmax><ymax>187</ymax></bndbox></object></annotation>