<annotation><folder>VOC2007</folder><filename>50_5639417343_20180629203533_20180630100000_163.jpg</filename><size><width>787</width><height>480</height><depth>3</depth></size><segmented>0</segmented><object><name /><pose>Unspecified</pose><truncated>0</truncated><difficult>0</difficult><bndbox><xmin>486</xmin><ymin>59</ymin><xmax>598</xmax><ymax>121</ymax></bndbox></object><object><name /><pose>Unspecified</pose><truncated>0</truncated><difficult>0</difficult><bndbox><xmin>256</xmin><ymin>311</ymin><xmax>390</xmax><ymax>410</ymax></bndbox></object><object><name /><pose>Unspecified</pose><truncated>0</truncated><difficult>0</difficult><bndbox><xmin>307</xmin><ymin>167</ymin><xmax>405</xmax><ymax>222</ymax></bndbox></object><object><name /><pose>Unspecified</pose><truncated>0</truncated><difficult>0</difficult><bndbox><xmin>128</xmin><ymin>112</ymin><xmax>435</xmax><ymax>159</ymax></bndbox></object><object><name /><pose>Unspecified</pose><truncated>0</truncated><difficult>0</difficult><bndbox><xmin>499</xmin><ymin>317</ymin><xmax>573</xmax><ymax>408</ymax></bndbox></object><object><name /><pose>Unspecified</pose><truncated>0</truncated><difficult>0</difficult><bndbox><xmin>117</xmin><ymin>171</ymin><xmax>217</xmax><ymax>220</ymax></bndbox></object><object><name /><pose>Unspecified</pose><truncated>0</truncated><difficult>0</difficult><bndbox><xmin>1</xmin><ymin>220</ymin><xmax>729</xmax><ymax>288</ymax></bndbox></object></annotation>